[
    {
        "_id": {
            "$oid": "5f7c9e70d9071a7ec9d5c2db"
        },
        "estadoInicial": "solicitada",
        "estadoFinal": "inhabilitada",
        "soloCOM": true,
        "modificaDestino": false
    },
    {
        "_id": {
            "$oid": "5f7c9e70d9071a7ec9d5c2dc"
        },
        "estadoInicial": "solicitada",
        "estadoFinal": "habilitada",
        "soloCOM": true,
        "modificaDestino": false
    },
    {
        "_id": {
            "$oid": "5f7c9e70d9071a7ec9d5c2dd"
        },
        "estadoInicial": "solicitada",
        "estadoFinal": "finalizada",
        "soloCOM": true,
        "modificaDestino": false
    },
    {
        "_id": {
            "$oid": "5f7c9e70d9071a7ec9d5c2de"
        },
        "estadoInicial": "habilitada",
        "estadoFinal": "asignada",
        "soloCOM": true,
        "modificaDestino": true
    },
    {
        "_id": {
            "$oid": "5f7c9e70d9071a7ec9d5c2df"
        },
        "estadoInicial": "habilitada",
        "estadoFinal": "finalizada",
        "soloCOM": true,
        "modificaDestino": false
    },
    {
        "_id": {
            "$oid": "5f7c9e70d9071a7ec9d5c2e0"
        },
        "estadoInicial": "asignada",
        "estadoFinal": "habilitada",
        "soloCOM": true,
        "modificaDestino": false
    },
    {
        "_id": {
            "$oid": "5f7c9e70d9071a7ec9d5c2e1"
        },
        "estadoInicial": "asignada",
        "estadoFinal": "aceptada",
        "soloCOM": false,
        "modificaDestino": false
    },
    {
        "_id": {
            "$oid": "5f7c9e70d9071a7ec9d5c2e2"
        },
        "estadoInicial": "asignada",
        "estadoFinal": "rechazada",
        "soloCOM": false,
        "modificaDestino": false
    },
    {
        "_id": {
            "$oid": "5f7c9e70d9071a7ec9d5c2e3"
        },
        "estadoInicial": "asignada",
        "estadoFinal": "finalizada",
        "soloCOM": true,
        "modificaDestino": false
    },
    {
        "_id": {
            "$oid": "5f7c9e70d9071a7ec9d5c2e4"
        },
        "estadoInicial": "aceptada",
        "estadoFinal": "finalizada",
        "soloCOM": true,
        "modificaDestino": false
    },
    {
        "_id": {
            "$oid": "5f7c9e70d9071a7ec9d5c2e5"
        },
        "estadoInicial": "rechazada",
        "estadoFinal": "finalizada",
        "soloCOM": true,
        "modificaDestino": false
    },
    {
        "_id": {
            "$oid": "5f7c9e70d9071a7ec9d5c2e6"
        },
        "estadoInicial": "rechazada",
        "estadoFinal": "asignada",
        "soloCOM": true,
        "modificaDestino": true
    },
    {
        "_id": {
            "$oid": "5f7c9e70d9071a7ec9d5c2e7"
        },
        "estadoInicial": "asignada",
        "estadoFinal": "encomendada",
        "soloCOM": true,
        "modificaDestino": false
    },
    {
        "_id": {
            "$oid": "5f7c9e70d9071a7ec9d5c2e8"
        },
        "estadoInicial": "encomendada",
        "estadoFinal": "finalizada",
        "soloCOM": true,
        "modificaDestino": false
    },
    {
        "_id": {
            "$oid": "5f7c9e70d9071a7ec9d5c2e9"
        },
        "estadoInicial": "inhabilitada",
        "estadoFinal": "finalizada",
        "soloCOM": true,
        "modificaDestino": false
    }
]